pic2asc/__init__.py
pic2asc/color.py
pic2asc/pic2asc.py
pic2asc-0.0.2.dist-info/LICENSE
pic2asc-0.0.2.dist-info/METADATA
pic2asc-0.0.2.dist-info/WHEEL
pic2asc-0.0.2.dist-info/entry_points.txt
pic2asc-0.0.2.dist-info/top_level.txt
pic2asc-0.0.2.dist-info/RECORD
