Metadata-Version: 2.1
Name: pic2asc
Version: 0.0.2
Summary: turn pic to ascii with color
License: MIT License
Project-URL: Source, https://github.com/Boooooom030/pic2asc
Keywords: ascii art,picture
Classifier: Development Status :: 4 - Beta
Classifier: Programming Language :: Python :: 3
Classifier: Programming Language :: Python :: 3.12
Classifier: Programming Language :: Python :: 3 :: Only
Requires-Python: >=3.12
License-File: LICENSE
Requires-Dist: Pillow
